file_manipulation.cpython-36m-darwin.so
albatradis/AlbaTraDIS.py
albatradis/AlbaTraDISArtemisProject.py
albatradis/AlbaTraDISGeneReports.py
albatradis/AlbaTraDISPresenceAbsence.py
albatradis/AlbaTraDISScatterPlot.py
albatradis/ArtemisProject.py
albatradis/Block.py
albatradis/BlockIdentifier.py
albatradis/BlockInsertions.py
albatradis/EMBLExpandGenes.py
albatradis/EMBLGenerator.py
albatradis/EMBLReader.py
albatradis/EMBLSequence.py
albatradis/ExperimentCollection.py
albatradis/ExperimentMetaData.py
albatradis/Gene.py
albatradis/GeneAnnotator.py
albatradis/GeneReport.py
albatradis/GeneReportSets.py
albatradis/GeneToFiles.py
albatradis/HeatMap.py
albatradis/NormalisePlots.py
albatradis/PlotGenerator.py
albatradis/PlotLog.py
albatradis/PlotMasking.py
albatradis/PlotParser.py
albatradis/PrepareEMBLFile.py
albatradis/PrepareInputFiles.py
albatradis/PresenceAbsence.py
albatradis/ReorderGenes.py
albatradis/ScatterPlot.py
albatradis/TradisComparison.py
albatradis/TradisEssentiality.py
albatradis/TradisGeneInsertSites.py
albatradis/Window.py
albatradis/WindowGenerator.py
albatradis/__init__.py
albatradis-1.0.1.data/scripts/albatradis
albatradis-1.0.1.data/scripts/albatradis-annotation
albatradis-1.0.1.data/scripts/albatradis-artemis_project
albatradis-1.0.1.data/scripts/albatradis-gene_reports
albatradis-1.0.1.data/scripts/albatradis-presence_absence
albatradis-1.0.1.data/scripts/albatradis-scatterplot
albatradis-1.0.1.dist-info/DESCRIPTION.rst
albatradis-1.0.1.dist-info/METADATA
albatradis-1.0.1.dist-info/RECORD
albatradis-1.0.1.dist-info/WHEEL
albatradis-1.0.1.dist-info/metadata.json
albatradis-1.0.1.dist-info/top_level.txt
