Metadata-Version: 2.0
Name: albatradis
Version: 1.0.1
Summary: Comparitive transposon mutagenesis experiment analysis
Home-page: https://github.com/quadram-institute-bioscience/albatradis
Author: Andrew J. Page
Author-email: andrew.page@quadram.ac.uk
License: GPLv3
Platform: UNKNOWN
Classifier: Development Status :: 4 - Beta
Classifier: Intended Audience :: Science/Research
Classifier: Topic :: Scientific/Engineering :: Bio-Informatics
Classifier: Programming Language :: Python :: 3 :: Only
Classifier: License :: OSI Approved :: GNU General Public License v3 (GPLv3)
Requires-Dist: biopython (>=1.68)
Requires-Dist: pyfastaq (>=3.12.0)
Requires-Dist: scipy
Requires-Dist: numpy
Requires-Dist: dendropy
Requires-Dist: seaborn
Requires-Dist: pandas
Requires-Dist: graphviz
Requires-Dist: cython
